confight.py
confight-2.0.dist-info/LICENSE
confight-2.0.dist-info/METADATA
confight-2.0.dist-info/WHEEL
confight-2.0.dist-info/entry_points.txt
confight-2.0.dist-info/top_level.txt
confight-2.0.dist-info/RECORD
