Metadata-Version: 2.1
Name: confight
Version: 2.0
Summary: Common config loading for Python and the command line
Home-page: https://github.com/avature/confight
Author: Avature
Author-email: platform@avature.net
License: MIT
Keywords: config configuration droplets toml json ini yaml
Classifier: Programming Language :: Python :: 3.8
Classifier: Programming Language :: Python :: 3.9
Classifier: Programming Language :: Python :: 3.10
Classifier: Programming Language :: Python :: 3.11
Classifier: License :: OSI Approved :: MIT License
Classifier: Operating System :: OS Independent
License-File: LICENSE
Requires-Dist: toml
Requires-Dist: setuptools
Provides-Extra: hcl
Requires-Dist: pyhcl ; extra == 'hcl'
Provides-Extra: yaml
Requires-Dist: ruamel.yaml (>=0.18.0) ; extra == 'yaml'
